pypi_test_pkg/__init__.py
pypi_test_pkg/math.py
pypijhjoh-0.3.5.dist-info/LICENSE
pypijhjoh-0.3.5.dist-info/METADATA
pypijhjoh-0.3.5.dist-info/WHEEL
pypijhjoh-0.3.5.dist-info/top_level.txt
pypijhjoh-0.3.5.dist-info/RECORD
