Metadata-Version: 2.1
Name: pypijhjoh
Version: 0.3.5
Summary: Test package by jhjoh
Home-page: UNKNOWN
Author: Joakim Johansen
Author-email: jhjoh@equinor.com
License: MIT
Keywords: TEST,PYPI
Platform: UNKNOWN
Classifier: Programming Language :: Python :: 3
Classifier: License :: OSI Approved :: MIT License
Classifier: Operating System :: OS Independent
Requires-Python: >=3.6
Requires-Dist: numpy
